get_docker_secret.py
docker_secret_getter-1.0.2.dist-info/LICENSE.txt
docker_secret_getter-1.0.2.dist-info/METADATA
docker_secret_getter-1.0.2.dist-info/WHEEL
docker_secret_getter-1.0.2.dist-info/top_level.txt
docker_secret_getter-1.0.2.dist-info/RECORD
