Metadata-Version: 2.1
Name: docker-secret-getter
Version: 1.0.2
Summary: Utility function to fetch docker secrets/envvars. Fork of https://github.com/Fischerfredl/get-docker-secret
Home-page: https://github.com/sajadrahimi/get-docker-secret
Author: Sajad Rahimi
Author-email: rahimisajad@outlook.com
License: MIT
Keywords: docker,secret,envvar,config
Platform: UNKNOWN
Classifier: License :: OSI Approved :: MIT License
Classifier: Programming Language :: Python :: 2.7
Classifier: Programming Language :: Python :: 3.6
Classifier: Programming Language :: Python :: 3.7
Classifier: Programming Language :: Python :: 3.8
Classifier: Programming Language :: Python :: 3.9
License-File: LICENSE.txt
